LyScriptTools32/__init__.py
LyScriptTools32-1.0.6.dist-info/LICENSE
LyScriptTools32-1.0.6.dist-info/METADATA
LyScriptTools32-1.0.6.dist-info/WHEEL
LyScriptTools32-1.0.6.dist-info/top_level.txt
LyScriptTools32-1.0.6.dist-info/RECORD
